igrade/API.py
igrade/__init__.py
igrade/exceptions.py
igrade/utils.py
igrade-2.7.0.dist-info/LICENSE
igrade-2.7.0.dist-info/METADATA
igrade-2.7.0.dist-info/WHEEL
igrade-2.7.0.dist-info/top_level.txt
igrade-2.7.0.dist-info/RECORD
